{
    "id": 5438237,
    "title": "Aidan_mac_Kinsley.jpg",
    "slug": null,
    "state": "public",
    "isWip": null,
    "isDraft": null,
    "entityClass": "Image",
    "icon": "fa-solid fa-image",
    "url": "https://www.worldanvil.com/uploads/images/d4e48eda300fa545224c8c14275c2c7c.jpg",
    "subscribergroups": [],
    "folderId": "8627009f-ffbf-4163-9eff-4e41b4e59ef8",
    "tags": "",
    "updateDate": {
        "date": "2025-10-15 07:23:06.000000",
        "timezone_type": 3,
        "timezone": "Europe/London"
    },
    "filename": "d4e48eda300fa545224c8c14275c2c7c.jpg",
    "path": "/uploads/images",
    "size": 467430,
    "width": 508,
    "height": 901,
    "extension": "jpg",
    "description": "@[Эйдан мак Кинсли](person:9a7216ab-35fe-45e8-a3c5-066ed1a149ca)",
    "alt": null,
    "creditArtistName": null,
    "creditArtistWebsite": null,
    "creditArtTitle": null,
    "creditArtUrl": null,
    "creationDate": {
        "date": "2024-03-15 21:00:16.000000",
        "timezone_type": 3,
        "timezone": "Europe/London"
    },
    "views": 2,
    "likes": null,
    "isFeatured": false,
    "linkUrl": null,
    "pageUrl": "https://www.worldanvil.com/i/5438237",
    "isEditable": true,
    "success": true
}